tomlguard/__init__.py
tomlguard/base.py
tomlguard/error.py
tomlguard/tomlguard.py
tomlguard/__tests/test_iterproxy.py
tomlguard/__tests/test_loader.py
tomlguard/__tests/test_proxy.py
tomlguard/__tests/test_proxy_entry.py
tomlguard/__tests/test_tomlguard.py
tomlguard/__tests/__data/data.toml
tomlguard/__tests/__data/data_second.toml
tomlguard/utils/__init__.py
tomlguard/utils/iter_proxy.py
tomlguard/utils/loader.py
tomlguard/utils/proxy.py
tomlguard/utils/proxy_mixin.py
tomlguard/utils/trace_helper.py
tomlguard/utils/writing.py
tomlguard-0.4.0.dist-info/LICENSE
tomlguard-0.4.0.dist-info/METADATA
tomlguard-0.4.0.dist-info/WHEEL
tomlguard-0.4.0.dist-info/top_level.txt
tomlguard-0.4.0.dist-info/RECORD
