Metadata-Version: 2.1
Name: tomlguard
Version: 0.4.0
Author: John Grey
Author-email: jgrey.n.plus.one@gmail.com
License: ACAB License © 2022-12-06 John Grey
Project-URL: homepage, https://github.com/jgrey4296/tomlguard
Project-URL: documentation, https://github.com/jgrey4296/tomlguard/wiki
Project-URL: repository, https://github.com/jgrey4296/tomlguard
Project-URL: changelog, https://github.com//jgrey4296/tomlguard/blob/master/CHANGELOG.md
Keywords: toml
Classifier: Programming Language :: Python
Classifier: Programming Language :: Python :: 3.10
Classifier: Programming Language :: Python :: 3.11
Classifier: Development Status :: 3 - Alpha
Classifier: Topic :: Utilities
Requires-Python: >=3.10
License-File: LICENSE
Requires-Dist: tomli-w
Requires-Dist: toml ; python_version < "3.11"
Provides-Extra: test
Requires-Dist: pytest >7.0.0 ; extra == 'test'
Requires-Dist: pytest-mock ; extra == 'test'
